datascience/AUDIO2HORUS.py
datascience/Adopt New Shipping Containers.py
datascience/AssesingData.py
datascience/Audit Logging.py
datascience/Averaging of Data.py
datascience/Build the time hub_links_ satelites.py
datascience/Building a Diagram for the Scheduling of Jobs.py
datascience/DATABASE2HORUS.py
datascience/Data Science (1).pdf
datascience/DataBinning_Bucketing.py
datascience/FixerUtility.py
datascience/Generating Reports.py
datascience/Global Post Codes in r studio.txt
datascience/JSON2HORUS.py
datascience/Loading IP_DATA_ALL.py
datascience/MOVIE2HORUSFrame.py
datascience/Organize-Horizontal.py
datascience/Organize-secure-vault.py
datascience/Outlier Detection.py
datascience/PICTURE2HORUS.py
datascience/PowerBI.txt
datascience/Program to connect to different data sourcessqllite.py
datascience/Rcodes.txt
datascience/Text delimited CSV to HORUS.py
datascience/Transform-Gunnarsson_is_Born.py
datascience/Understanding Your Online Visitor Data.py
datascience/Vermeulen PLC.py
datascience/XML processing.py
datascience/XML2HORUS.py
datascience/__init__.py
datascience/cassendra.txt
datascience/conenct to microsoftexcel.py
datascience/conenct to mysql.py
datascience/retrieve different attributes of data.py
datascience/testdb.py
datascience/01-Vermeulen/01-Retrieve/Logging/Logging_1da0cef2-73f6-4795-a420-b6ffbc553575.log
datascience/01-Vermeulen/02-Assess/Logging/Logging_db761fe0-d634-44ba-9532-be91c9614bfa.log
datascience/01-Vermeulen/03-Process/Logging/Logging_0e20a9ca-2fb8-41a3-8f39-61c1f40a6a7d.log
datascience/01-Vermeulen/04-Transform/Logging/Logging_17321725-f064-48fd-bdcf-7c6bed610019.log
datascience/01-Vermeulen/05-Organise/Logging/Logging_948c0f08-032d-4796-a152-c4a3d84aad6e.log
datascience/01-Vermeulen/06-Report/Logging/Logging_88dba01d-c315-439e-89d6-eaedd11cada0.log
datascience/02-Krennwallner/01-Retrieve/Logging/Logging_febce279-855c-4107-8cbe-4bfaf707999c.log
datascience/02-Krennwallner/02-Assess/Logging/Logging_08bc8e94-d8b8-49a6-9033-dbe0eeca50f4.log
datascience_jyoti-0.3.0.dist-info/licenses/LICENSE
datascience_jyoti-0.3.0.dist-info/METADATA
datascience_jyoti-0.3.0.dist-info/WHEEL
datascience_jyoti-0.3.0.dist-info/top_level.txt
datascience_jyoti-0.3.0.dist-info/RECORD
