Metadata-Version: 2.4
Name: datascience-jyoti
Version: 0.3.0
Summary: Data Science practicals and utilities - Python scripts
Author: Jyoti Rahate
Author-email: your.email@example.com
Classifier: Programming Language :: Python :: 3
Classifier: License :: OSI Approved :: MIT License
Classifier: Operating System :: OS Independent
Requires-Python: >=3.7
License-File: LICENSE
Dynamic: author
Dynamic: author-email
Dynamic: classifier
Dynamic: description
Dynamic: license-file
Dynamic: requires-python
Dynamic: summary
